src/alu_control.v
module alu_control (
    input [1:0] ALUOp,
    input [2:0] funct3,
    input       funct7_5,
    output reg [3:0] alu_control
);

    // === ALU Control Codes ===
    localparam ALU_AND  = 4'b0000;
    localparam ALU_OR   = 4'b0001;
    localparam ALU_ADD  = 4'b0010;
    localparam ALU_SUB  = 4'b0110;
    localparam ALU_SLT  = 4'b0111;
    localparam ALU_XOR  = 4'b1000;
    localparam ALU_SLL  = 4'b1001;
    localparam ALU_SRL  = 4'b1010;
    localparam ALU_SRA  = 4'b1011;
    localparam ALU_SLTU = 4'b1100;
    localparam ALU_INV  = 4'b1111; // Illegal operation

    always @(*) begin
        alu_control = ALU_INV; // default to illegal

        if (ALUOp == 2'b10) begin // R-type
            case (funct3)
                3'b000: alu_control = (funct7_5) ? ALU_SUB : ALU_ADD;
                3'b111: alu_control = ALU_AND;
                3'b110: alu_control = ALU_OR;
                3'b100: alu_control = ALU_XOR;
                3'b001: alu_control = ALU_SLL;
                3'b101: alu_control = (funct7_5) ? ALU_SRA : ALU_SRL;
                3'b010: alu_control = ALU_SLT;
                3'b011: alu_control = ALU_SLTU;
            endcase
        end
    end

endmodule

alu_control_tb.v
`timescale 1ns/1ps

module alu_control_tb;

    // Inputs
    reg [1:0] ALUOp;
    reg [2:0] funct3;
    reg       funct7_5;

    // Output
    wire [3:0] alu_control;

    // Instantiate the Unit Under Test (UUT)
    alu_control uut (
        .ALUOp(ALUOp),
        .funct3(funct3),
        .funct7_5(funct7_5),
        .alu_control(alu_control)
    );

    // Waveform dump (for ModelSim or GTKWave via VCD)
    initial begin
        $dumpfile("alu_control_tb.vcd");
        $dumpvars(0, alu_control_tb);
    end

    // Self-checking task
    task test;
        input [1:0] op;
        input [2:0] f3;
        input       f7;
        input [3:0] expected;

        begin
            ALUOp    = op;
            funct3   = f3;
            funct7_5 = f7;
            #5; // Allow time for signals to propagate

            if (alu_control !== expected)
                $display("[FAIL] ALUOp=%b funct3=%b funct7_5=%b => alu_control=%b (expected %b)", op, f3, f7, alu_control, expected);
            else
                $display("[PASS] ALUOp=%b funct3=%b funct7_5=%b => alu_control=%b", op, f3, f7, alu_control);
        end
    endtask

    // Run tests
    initial begin
        // R-type tests
        test(2'b10, 3'b000, 1'b0, 4'b0010); // ADD
        test(2'b10, 3'b000, 1'b1, 4'b0110); // SUB
        test(2'b10, 3'b111, 1'b0, 4'b0000); // AND
        test(2'b10, 3'b110, 1'b0, 4'b0001); // OR
        test(2'b10, 3'b100, 1'b0, 4'b1000); // XOR
        test(2'b10, 3'b001, 1'b0, 4'b1001); // SLL
        test(2'b10, 3'b101, 1'b0, 4'b1010); // SRL
        test(2'b10, 3'b101, 1'b1, 4'b1011); // SRA
        test(2'b10, 3'b010, 1'b0, 4'b0111); // SLT
        test(2'b10, 3'b011, 1'b0, 4'b1100); // SLTU

        // I-type tests
        test(2'b11, 3'b000, 1'b0, 4'b0010); // ADDI
        test(2'b11, 3'b111, 1'b0, 4'b0000); // ANDI
        test(2'b11, 3'b110, 1'b0, 4'b0001); // ORI
        test(2'b11, 3'b100, 1'b0, 4'b1000); // XORI
        test(2'b11, 3'b001, 1'b0, 4'b1001); // SLLI
        test(2'b11, 3'b101, 1'b0, 4'b1010); // SRLI
        test(2'b11, 3'b101, 1'b1, 4'b1011); // SRAI
        test(2'b11, 3'b010, 1'b0, 4'b0111); // SLTI
        test(2'b11, 3'b011, 1'b0, 4'b1100); // SLTIU

        // Branching tests
        test(2'b01, 3'b000, 1'b0, 4'b0110); // BEQ
        test(2'b01, 3'b001, 1'b0, 4'b0110); // BNE
        test(2'b01, 3'b100, 1'b0, 4'b0111); // BLT
        test(2'b01, 3'b101, 1'b0, 4'b0111); // BGE
        test(2'b01, 3'b110, 1'b0, 4'b1100); // BLTU
        test(2'b01, 3'b111, 1'b0, 4'b1100); // BGEU

        // Load/Store test
        test(2'b00, 3'b000, 1'b0, 4'b0010); // LW/SW → ADD

        $finish;
    end

endmodule

alu_control_tb.vcd
$date
	Mon May 26 11:28:44 2025
$end
$version
	ModelSim Version 2020.1
$end
$timescale
	1ps
$end

$scope module alu_control_tb $end
$var reg 2 ! ALUOp [1:0] $end
$var reg 3 " funct3 [2:0] $end
$var reg 1 # funct7_5 $end
$var wire 1 $ alu_control [3] $end
$var wire 1 % alu_control [2] $end
$var wire 1 & alu_control [1] $end
$var wire 1 ' alu_control [0] $end

$scope task test $end
$var reg 2 ( op [1:0] $end
$var reg 3 ) f3 [2:0] $end
$var reg 1 * f7 $end
$var reg 4 + expected [3:0] $end
$upscope $end

$scope module uut $end
$var wire 1 , ALUOp [1] $end
$var wire 1 - ALUOp [0] $end
$var wire 1 . funct3 [2] $end
$var wire 1 / funct3 [1] $end
$var wire 1 0 funct3 [0] $end
$var wire 1 1 funct7_5 $end
$var reg 4 2 alu_control [3:0] $end
$upscope $end
$upscope $end
$enddefinitions $end
#0
$dumpvars
b10 !
b0 "
0#
b10 2
b10 (
b0 )
0*
b10 +
0'
1&
0%
0$
01
00
0/
0.
0-
1,
$end
#5000
1*
b110 +
1#
11
b0 2
b110 2
1%
#10000
b111 )
0*
b0 +
b111 "
0#
10
1/
1.
01
b0 2
0&
0%
#15000
b110 )
b1 +
b110 "
00
b1 2
1'
#20000
b100 )
b1000 +
b100 "
0/
b0 2
b1000 2
0'
1$
#25000
b1 )
b1001 +
b1 "
10
0.
b0 2
b1001 2
1'
#30000
b101 )
b1010 +
b101 "
1.
b0 2
b1010 2
0'
1&
#35000
1*
b1011 +
1#
11
b0 2
b1011 2
1'
#40000
b10 )
0*
b111 +
b10 "
0#
00
1/
0.
01
b0 2
b111 2
1%
0$
#45000
b11 )
b1100 +
b11 "
10
b0 2
b1100 2
0'
0&
1$
#50000
b11 (
b0 )
b10 +
b11 !
b0 "
00
0/
1-
b0 2
b10 2
1&
0%
0$
#55000
b111 )
b0 +
b111 "
10
1/
1.
b0 2
0&
#60000
b110 )
b1 +
b110 "
00
b1 2
1'
#65000
b100 )
b1000 +
b100 "
0/
b0 2
b1000 2
0'
1$
#70000
b1 )
b1001 +
b1 "
10
0.
b0 2
b1001 2
1'
#75000
b101 )
b1010 +
b101 "
1.
b0 2
b1010 2
0'
1&
#80000
1*
b1011 +
1#
11
b0 2
b1011 2
1'
#85000
b10 )
0*
b111 +
b10 "
0#
00
1/
0.
01
b0 2
b111 2
1%
0$
#90000
b11 )
b1100 +
b11 "
10
b0 2
b1100 2
0'
0&
1$
#95000
b1 (
b0 )
b110 +
b1 !
b0 "
00
0/
0,
b0 2
b110 2
1&
0$
#100000
b1 )
b1 "
10
b0 2
b110 2
#105000
b100 )
b111 +
b100 "
00
1.
b0 2
b111 2
1'
#110000
b101 )
b101 "
10
b0 2
b111 2
#115000
b110 )
b1100 +
b110 "
00
1/
b0 2
b1100 2
0'
0&
1$
#120000
b111 )
b111 "
10
b0 2
b1100 2
#125000
b0 (
b0 )
b10 +
b0 !
b0 "
00
0/
0.
0-
b0 2
b10 2
1&
0%
0$
