src/alu.v
module alu (
    input  [63:0] a,
    input  [63:0] b,
    input  [3:0]  alu_control,
    output        zero,
    output reg [63:0] ALUresult
);

    // Output 1 if result is zero
    assign zero = (ALUresult == 64'b0);

    always @(*) begin
        case (alu_control)
            4'b0000: ALUresult = a & b;                  // AND
            4'b0001: ALUresult = a | b;                  // OR
            4'b0010: ALUresult = a + b;                  // ADD
            4'b0110: ALUresult = a - b;                  // SUB
            4'b0111: ALUresult = ($signed(a) < $signed(b)) ? 64'b1 : 64'b0; // SLT
            4'b1000: ALUresult = a ^ b;                  // XOR
            4'b1001: ALUresult = a << b[5:0];            // SLL (lower 6 bits only)
            4'b1010: ALUresult = a >> b[5:0];            // SRL
            4'b1011: ALUresult = $signed(a) >>> b[5:0];  // SRA
            4'b1100: ALUresult = (a < b) ? 64'b1 : 64'b0; // SLTU
            default: ALUresult = 64'b0;                  // Safe default
        endcase
    end

endmodule

alu_tb.v
`timescale 1ns/1ps

module alu_tb;

    // Inputs
    reg  [63:0] a, b;
    reg  [3:0]  alu_control;

    // Outputs
    wire        zero;
    wire [63:0] ALUresult;

    // Instantiate the Unit Under Test (UUT)
    alu uut (
        .a(a),
        .b(b),
        .alu_control(alu_control),
        .zero(zero),
        .ALUresult(ALUresult)
    );

    // Waveform dump
    initial begin
        $dumpfile("alu_tb.vcd");
        $dumpvars(0, alu_tb);
    end

    // Self-checking task
    task test;
        input [63:0] in_a, in_b;
        input [3:0]  ctrl;
        input [63:0] expected;
        begin
            a = in_a;
            b = in_b;
            alu_control = ctrl;
            #5;
            if (ALUresult !== expected)
                $display("[FAIL] ctrl=%b a=%0d b=%0d → result=%0d (expected %0d)", ctrl, in_a, in_b, ALUresult, expected);
            else
                $display("[PASS] ctrl=%b a=%0d b=%0d → result=%0d", ctrl, in_a, in_b, ALUresult);
        end
    endtask

    // Run tests
    initial begin
        // AND
        test(64'hFF00FF00FF00FF00, 64'h0F0F0F0F0F0F0F0F, 4'b0000, 64'h0F000F000F000F00);

        // OR
        test(64'hFF00FF00FF00FF00, 64'h0F0F0F0F0F0F0F0F, 4'b0001, 64'hFF0FFF0FFF0FFF0F);

        // ADD
        test(64'd10, 64'd5, 4'b0010, 64'd15);

        // SUB
        test(64'd10, 64'd5, 4'b0110, 64'd5);

        // SLT (signed)
        test(-5, 1, 4'b0111, 1);     // true
        test(5, -1, 4'b0111, 0);     // false

        // XOR
        test(64'hF0F0F0F0F0F0F0F0, 64'h0F0F0F0F0F0F0F0F, 4'b1000, 64'hFFFFFFFFFFFFFFFF);

        // SLL (logical left shift)
        test(64'd1, 64'd4, 4'b1001, 64'd16);  // 1 << 4 = 16

        // SRL (logical right shift)
        test(64'd16, 64'd2, 4'b1010, 64'd4);  // 16 >> 2 = 4

        // SRA (arithmetic right shift)
        test(-8, 64'd1, 4'b1011, -4); // -8 >>> 1 = -4

        // SLTU (unsigned comparison)
        test(64'd5, 64'd10, 4'b1100, 64'd1);
        test(64'd15, 64'd10, 4'b1100, 64'd0);

        // Zero flag test
        test(64'd5, 64'd5, 4'b0110, 64'd0); // SUB → zero flag should be 1

        $finish;
    end

endmodule

alu_tb.vcd
$date
	Mon May 26 11:43:27 2025
$end
$version
	ModelSim Version 2020.1
$end
$timescale
	1ps
$end

$scope module alu_tb $end
$var reg 64 ! a [63:0] $end
$var reg 64 " b [63:0] $end
$var reg 4 # alu_control [3:0] $end
$var wire 1 $ zero $end
$var wire 1 % ALUresult [63] $end
$var wire 1 & ALUresult [62] $end
$var wire 1 ' ALUresult [61] $end
$var wire 1 ( ALUresult [60] $end
$var wire 1 ) ALUresult [59] $end
$var wire 1 * ALUresult [58] $end
$var wire 1 + ALUresult [57] $end
$var wire 1 , ALUresult [56] $end
$var wire 1 - ALUresult [55] $end
$var wire 1 . ALUresult [54] $end
$var wire 1 / ALUresult [53] $end
$var wire 1 0 ALUresult [52] $end
$var wire 1 1 ALUresult [51] $end
$var wire 1 2 ALUresult [50] $end
$var wire 1 3 ALUresult [49] $end
$var wire 1 4 ALUresult [48] $end
$var wire 1 5 ALUresult [47] $end
$var wire 1 6 ALUresult [46] $end
$var wire 1 7 ALUresult [45] $end
$var wire 1 8 ALUresult [44] $end
$var wire 1 9 ALUresult [43] $end
$var wire 1 : ALUresult [42] $end
$var wire 1 ; ALUresult [41] $end
$var wire 1 < ALUresult [40] $end
$var wire 1 = ALUresult [39] $end
$var wire 1 > ALUresult [38] $end
$var wire 1 ? ALUresult [37] $end
$var wire 1 @ ALUresult [36] $end
$var wire 1 A ALUresult [35] $end
$var wire 1 B ALUresult [34] $end
$var wire 1 C ALUresult [33] $end
$var wire 1 D ALUresult [32] $end
$var wire 1 E ALUresult [31] $end
$var wire 1 F ALUresult [30] $end
$var wire 1 G ALUresult [29] $end
$var wire 1 H ALUresult [28] $end
$var wire 1 I ALUresult [27] $end
$var wire 1 J ALUresult [26] $end
$var wire 1 K ALUresult [25] $end
$var wire 1 L ALUresult [24] $end
$var wire 1 M ALUresult [23] $end
$var wire 1 N ALUresult [22] $end
$var wire 1 O ALUresult [21] $end
$var wire 1 P ALUresult [20] $end
$var wire 1 Q ALUresult [19] $end
$var wire 1 R ALUresult [18] $end
$var wire 1 S ALUresult [17] $end
$var wire 1 T ALUresult [16] $end
$var wire 1 U ALUresult [15] $end
$var wire 1 V ALUresult [14] $end
$var wire 1 W ALUresult [13] $end
$var wire 1 X ALUresult [12] $end
$var wire 1 Y ALUresult [11] $end
$var wire 1 Z ALUresult [10] $end
$var wire 1 [ ALUresult [9] $end
$var wire 1 \ ALUresult [8] $end
$var wire 1 ] ALUresult [7] $end
$var wire 1 ^ ALUresult [6] $end
$var wire 1 _ ALUresult [5] $end
$var wire 1 ` ALUresult [4] $end
$var wire 1 a ALUresult [3] $end
$var wire 1 b ALUresult [2] $end
$var wire 1 c ALUresult [1] $end
$var wire 1 d ALUresult [0] $end

$scope task test $end
$var reg 64 e in_a [63:0] $end
$var reg 64 f in_b [63:0] $end
$var reg 4 g ctrl [3:0] $end
$var reg 64 h expected [63:0] $end
$upscope $end

$scope module uut $end
$var wire 1 i a [63] $end
$var wire 1 j a [62] $end
$var wire 1 k a [61] $end
$var wire 1 l a [60] $end
$var wire 1 m a [59] $end
$var wire 1 n a [58] $end
$var wire 1 o a [57] $end
$var wire 1 p a [56] $end
$var wire 1 q a [55] $end
$var wire 1 r a [54] $end
$var wire 1 s a [53] $end
$var wire 1 t a [52] $end
$var wire 1 u a [51] $end
$var wire 1 v a [50] $end
$var wire 1 w a [49] $end
$var wire 1 x a [48] $end
$var wire 1 y a [47] $end
$var wire 1 z a [46] $end
$var wire 1 { a [45] $end
$var wire 1 | a [44] $end
$var wire 1 } a [43] $end
$var wire 1 ~ a [42] $end
$var wire 1 !! a [41] $end
$var wire 1 "! a [40] $end
$var wire 1 #! a [39] $end
$var wire 1 $! a [38] $end
$var wire 1 %! a [37] $end
$var wire 1 &! a [36] $end
$var wire 1 '! a [35] $end
$var wire 1 (! a [34] $end
$var wire 1 )! a [33] $end
$var wire 1 *! a [32] $end
$var wire 1 +! a [31] $end
$var wire 1 ,! a [30] $end
$var wire 1 -! a [29] $end
$var wire 1 .! a [28] $end
$var wire 1 /! a [27] $end
$var wire 1 0! a [26] $end
$var wire 1 1! a [25] $end
$var wire 1 2! a [24] $end
$var wire 1 3! a [23] $end
$var wire 1 4! a [22] $end
$var wire 1 5! a [21] $end
$var wire 1 6! a [20] $end
$var wire 1 7! a [19] $end
$var wire 1 8! a [18] $end
$var wire 1 9! a [17] $end
$var wire 1 :! a [16] $end
$var wire 1 ;! a [15] $end
$var wire 1 <! a [14] $end
$var wire 1 =! a [13] $end
$var wire 1 >! a [12] $end
$var wire 1 ?! a [11] $end
$var wire 1 @! a [10] $end
$var wire 1 A! a [9] $end
$var wire 1 B! a [8] $end
$var wire 1 C! a [7] $end
$var wire 1 D! a [6] $end
$var wire 1 E! a [5] $end
$var wire 1 F! a [4] $end
$var wire 1 G! a [3] $end
$var wire 1 H! a [2] $end
$var wire 1 I! a [1] $end
$var wire 1 J! a [0] $end
$var wire 1 K! b [63] $end
$var wire 1 L! b [62] $end
$var wire 1 M! b [61] $end
$var wire 1 N! b [60] $end
$var wire 1 O! b [59] $end
$var wire 1 P! b [58] $end
$var wire 1 Q! b [57] $end
$var wire 1 R! b [56] $end
$var wire 1 S! b [55] $end
$var wire 1 T! b [54] $end
$var wire 1 U! b [53] $end
$var wire 1 V! b [52] $end
$var wire 1 W! b [51] $end
$var wire 1 X! b [50] $end
$var wire 1 Y! b [49] $end
$var wire 1 Z! b [48] $end
$var wire 1 [! b [47] $end
$var wire 1 \! b [46] $end
$var wire 1 ]! b [45] $end
$var wire 1 ^! b [44] $end
$var wire 1 _! b [43] $end
$var wire 1 `! b [42] $end
$var wire 1 a! b [41] $end
$var wire 1 b! b [40] $end
$var wire 1 c! b [39] $end
$var wire 1 d! b [38] $end
$var wire 1 e! b [37] $end
$var wire 1 f! b [36] $end
$var wire 1 g! b [35] $end
$var wire 1 h! b [34] $end
$var wire 1 i! b [33] $end
$var wire 1 j! b [32] $end
$var wire 1 k! b [31] $end
$var wire 1 l! b [30] $end
$var wire 1 m! b [29] $end
$var wire 1 n! b [28] $end
$var wire 1 o! b [27] $end
$var wire 1 p! b [26] $end
$var wire 1 q! b [25] $end
$var wire 1 r! b [24] $end
$var wire 1 s! b [23] $end
$var wire 1 t! b [22] $end
$var wire 1 u! b [21] $end
$var wire 1 v! b [20] $end
$var wire 1 w! b [19] $end
$var wire 1 x! b [18] $end
$var wire 1 y! b [17] $end
$var wire 1 z! b [16] $end
$var wire 1 {! b [15] $end
$var wire 1 |! b [14] $end
$var wire 1 }! b [13] $end
$var wire 1 ~! b [12] $end
$var wire 1 !" b [11] $end
$var wire 1 "" b [10] $end
$var wire 1 #" b [9] $end
$var wire 1 $" b [8] $end
$var wire 1 %" b [7] $end
$var wire 1 &" b [6] $end
$var wire 1 '" b [5] $end
$var wire 1 (" b [4] $end
$var wire 1 )" b [3] $end
$var wire 1 *" b [2] $end
$var wire 1 +" b [1] $end
$var wire 1 ," b [0] $end
$var wire 1 -" alu_control [3] $end
$var wire 1 ." alu_control [2] $end
$var wire 1 /" alu_control [1] $end
$var wire 1 0" alu_control [0] $end
$var wire 1 $ zero $end
$var reg 64 1" ALUresult [63:0] $end
$upscope $end
$upscope $end
$enddefinitions $end
#0
$dumpvars
b1111111100000000111111110000000011111111000000001111111100000000 !
b111100001111000011110000111100001111000011110000111100001111 "
b0 #
b111100000000000011110000000000001111000000000000111100000000 1"
b1111111100000000111111110000000011111111000000001111111100000000 e
b111100001111000011110000111100001111000011110000111100001111 f
b0 g
b111100000000000011110000000000001111000000000000111100000000 h
0$
0d
0c
0b
0a
0`
0_
0^
0]
1\
1[
1Z
1Y
0X
0W
0V
0U
0T
0S
0R
0Q
0P
0O
0N
0M
1L
1K
1J
1I
0H
0G
0F
0E
0D
0C
0B
0A
0@
0?
0>
0=
1<
1;
1:
19
08
07
06
05
04
03
02
01
00
0/
0.
0-
1,
1+
1*
1)
0(
0'
0&
0%
00"
0/"
0."
0-"
1,"
1+"
1*"
1)"
0("
0'"
0&"
0%"
1$"
1#"
1""
1!"
0~!
0}!
0|!
0{!
1z!
1y!
1x!
1w!
0v!
0u!
0t!
0s!
1r!
1q!
1p!
1o!
0n!
0m!
0l!
0k!
1j!
1i!
1h!
1g!
0f!
0e!
0d!
0c!
1b!
1a!
1`!
1_!
0^!
0]!
0\!
0[!
1Z!
1Y!
1X!
1W!
0V!
0U!
0T!
0S!
1R!
1Q!
1P!
1O!
0N!
0M!
0L!
0K!
0J!
0I!
0H!
0G!
0F!
0E!
0D!
0C!
1B!
1A!
1@!
1?!
1>!
1=!
1<!
1;!
0:!
09!
08!
07!
06!
05!
04!
03!
12!
11!
10!
1/!
1.!
1-!
1,!
1+!
0*!
0)!
0(!
0'!
0&!
0%!
0$!
0#!
1"!
1!!
1~
1}
1|
1{
1z
1y
0x
0w
0v
0u
0t
0s
0r
0q
1p
1o
1n
1m
1l
1k
1j
1i
$end
#5000
b1 g
b1111111100001111111111110000111111111111000011111111111100001111 h
b1 #
10"
b1111111100001111111111110000111111111111000011111111111100001111 1"
1d
1c
1b
1a
1X
1W
1V
1U
1T
1S
1R
1Q
1H
1G
1F
1E
1D
1C
1B
1A
18
17
16
15
14
13
12
11
1(
1'
1&
1%
#10000
b1010 e
b101 f
b10 g
b1111 h
b1010 !
b101 "
b10 #
00"
1/"
0+"
0)"
0$"
0#"
0""
0!"
0z!
0y!
0x!
0w!
0r!
0q!
0p!
0o!
0j!
0i!
0h!
0g!
0b!
0a!
0`!
0_!
0Z!
0Y!
0X!
0W!
0R!
0Q!
0P!
0O!
1I!
1G!
0B!
0A!
0@!
0?!
0>!
0=!
0<!
0;!
02!
01!
00!
0/!
0.!
0-!
0,!
0+!
0"!
0!!
0~
0}
0|
0{
0z
0y
0p
0o
0n
0m
0l
0k
0j
0i
b1111 1"
0\
0[
0Z
0Y
0X
0W
0V
0U
0T
0S
0R
0Q
0L
0K
0J
0I
0H
0G
0F
0E
0D
0C
0B
0A
0<
0;
0:
09
08
07
06
05
04
03
02
01
0,
0+
0*
0)
0(
0'
0&
0%
#15000
b110 g
b101 h
b110 #
1."
b101 1"
0c
0a
#20000
b1111111111111111111111111111111111111111111111111111111111111011 e
b1 f
b111 g
b1 h
b1111111111111111111111111111111111111111111111111111111111111011 !
b1 "
b111 #
10"
0*"
1J!
1F!
1E!
1D!
1C!
1B!
1A!
1@!
1?!
1>!
1=!
1<!
1;!
1:!
19!
18!
17!
16!
15!
14!
13!
12!
11!
10!
1/!
1.!
1-!
1,!
1+!
1*!
1)!
1(!
1'!
1&!
1%!
1$!
1#!
1"!
1!!
1~
1}
1|
1{
1z
1y
1x
1w
1v
1u
1t
1s
1r
1q
1p
1o
1n
1m
1l
1k
1j
1i
b1 1"
0b
#25000
b101 e
b1111111111111111111111111111111111111111111111111111111111111111 f
b0 h
b101 !
b1111111111111111111111111111111111111111111111111111111111111111 "
1+"
1*"
1)"
1("
1'"
1&"
1%"
1$"
1#"
1""
1!"
1~!
1}!
1|!
1{!
1z!
1y!
1x!
1w!
1v!
1u!
1t!
1s!
1r!
1q!
1p!
1o!
1n!
1m!
1l!
1k!
1j!
1i!
1h!
1g!
1f!
1e!
1d!
1c!
1b!
1a!
1`!
1_!
1^!
1]!
1\!
1[!
1Z!
1Y!
1X!
1W!
1V!
1U!
1T!
1S!
1R!
1Q!
1P!
1O!
1N!
1M!
1L!
1K!
0I!
1H!
0G!
0F!
0E!
0D!
0C!
0B!
0A!
0@!
0?!
0>!
0=!
0<!
0;!
0:!
09!
08!
07!
06!
05!
04!
03!
02!
01!
00!
0/!
0.!
0-!
0,!
0+!
0*!
0)!
0(!
0'!
0&!
0%!
0$!
0#!
0"!
0!!
0~
0}
0|
0{
0z
0y
0x
0w
0v
0u
0t
0s
0r
0q
0p
0o
0n
0m
0l
0k
0j
0i
b0 1"
1$
0d
#30000
b1111000011110000111100001111000011110000111100001111000011110000 e
b111100001111000011110000111100001111000011110000111100001111 f
b1000 g
b1111111111111111111111111111111111111111111111111111111111111111 h
b1111000011110000111100001111000011110000111100001111000011110000 !
b111100001111000011110000111100001111000011110000111100001111 "
b1000 #
00"
0/"
0."
1-"
0("
0'"
0&"
0%"
0~!
0}!
0|!
0{!
0v!
0u!
0t!
0s!
0n!
0m!
0l!
0k!
0f!
0e!
0d!
0c!
0^!
0]!
0\!
0[!
0V!
0U!
0T!
0S!
0N!
0M!
0L!
0K!
0J!
0H!
1F!
1E!
1D!
1C!
1>!
1=!
1<!
1;!
16!
15!
14!
13!
1.!
1-!
1,!
1+!
1&!
1%!
1$!
1#!
1|
1{
1z
1y
1t
1s
1r
1q
1l
1k
1j
1i
b1111111111111111111111111111111111111111111111111111111111111111 1"
0$
1d
1c
1b
1a
1`
1_
1^
1]
1\
1[
1Z
1Y
1X
1W
1V
1U
1T
1S
1R
1Q
1P
1O
1N
1M
1L
1K
1J
1I
1H
1G
1F
1E
1D
1C
1B
1A
1@
1?
1>
1=
1<
1;
1:
19
18
17
16
15
14
13
12
11
10
1/
1.
1-
1,
1+
1*
1)
1(
1'
1&
1%
#35000
b1 e
b100 f
b1001 g
b10000 h
b1 !
b100 "
b1001 #
10"
0,"
0+"
0)"
0$"
0#"
0""
0!"
0z!
0y!
0x!
0w!
0r!
0q!
0p!
0o!
0j!
0i!
0h!
0g!
0b!
0a!
0`!
0_!
0Z!
0Y!
0X!
0W!
0R!
0Q!
0P!
0O!
1J!
0F!
0E!
0D!
0C!
0>!
0=!
0<!
0;!
06!
05!
04!
03!
0.!
0-!
0,!
0+!
0&!
0%!
0$!
0#!
0|
0{
0z
0y
0t
0s
0r
0q
0l
0k
0j
0i
b10000 1"
0d
0c
0b
0a
0_
0^
0]
0\
0[
0Z
0Y
0X
0W
0V
0U
0T
0S
0R
0Q
0P
0O
0N
0M
0L
0K
0J
0I
0H
0G
0F
0E
0D
0C
0B
0A
0@
0?
0>
0=
0<
0;
0:
09
08
07
06
05
04
03
02
01
00
0/
0.
0-
0,
0+
0*
0)
0(
0'
0&
0%
#40000
b10000 e
b10 f
b1010 g
b100 h
b10000 !
b10 "
b1010 #
00"
1/"
1+"
0*"
0J!
1F!
b100 1"
1b
0`
#45000
b1111111111111111111111111111111111111111111111111111111111111000 e
b1 f
b1011 g
b1111111111111111111111111111111111111111111111111111111111111100 h
b1111111111111111111111111111111111111111111111111111111111111000 !
b1 "
b1011 #
10"
1,"
0+"
1G!
1E!
1D!
1C!
1B!
1A!
1@!
1?!
1>!
1=!
1<!
1;!
1:!
19!
18!
17!
16!
15!
14!
13!
12!
11!
10!
1/!
1.!
1-!
1,!
1+!
1*!
1)!
1(!
1'!
1&!
1%!
1$!
1#!
1"!
1!!
1~
1}
1|
1{
1z
1y
1x
1w
1v
1u
1t
1s
1r
1q
1p
1o
1n
1m
1l
1k
1j
1i
b1111111111111111111111111111111111111111111111111111111111111100 1"
1a
1`
1_
1^
1]
1\
1[
1Z
1Y
1X
1W
1V
1U
1T
1S
1R
1Q
1P
1O
1N
1M
1L
1K
1J
1I
1H
1G
1F
1E
1D
1C
1B
1A
1@
1?
1>
1=
1<
1;
1:
19
18
17
16
15
14
13
12
11
10
1/
1.
1-
1,
1+
1*
1)
1(
1'
1&
1%
#50000
b101 e
b1010 f
b1100 g
b1 h
b101 !
b1010 "
b1100 #
00"
0/"
1."
0,"
1+"
1)"
1J!
1H!
0G!
0F!
0E!
0D!
0C!
0B!
0A!
0@!
0?!
0>!
0=!
0<!
0;!
0:!
09!
08!
07!
06!
05!
04!
03!
02!
01!
00!
0/!
0.!
0-!
0,!
0+!
0*!
0)!
0(!
0'!
0&!
0%!
0$!
0#!
0"!
0!!
0~
0}
0|
0{
0z
0y
0x
0w
0v
0u
0t
0s
0r
0q
0p
0o
0n
0m
0l
0k
0j
0i
b1 1"
1d
0b
0a
0`
0_
0^
0]
0\
0[
0Z
0Y
0X
0W
0V
0U
0T
0S
0R
0Q
0P
0O
0N
0M
0L
0K
0J
0I
0H
0G
0F
0E
0D
0C
0B
0A
0@
0?
0>
0=
0<
0;
0:
09
08
07
06
05
04
03
02
01
00
0/
0.
0-
0,
0+
0*
0)
0(
0'
0&
0%
#55000
b1111 e
b0 h
b1111 !
1I!
1G!
b0 1"
1$
0d
#60000
b101 e
b101 f
b110 g
b101 !
b101 "
b110 #
1/"
0-"
1,"
0+"
1*"
0)"
0I!
0G!
